rnastructure_wrapper/__init__.py
rnastructure_wrapper/main.py
rnastructure_wrapper-0.0.0.dist-info/LICENSE
rnastructure_wrapper-0.0.0.dist-info/METADATA
rnastructure_wrapper-0.0.0.dist-info/WHEEL
rnastructure_wrapper-0.0.0.dist-info/top_level.txt
rnastructure_wrapper-0.0.0.dist-info/RECORD
