Metadata-Version: 2.1
Name: rnastructure_wrapper
Version: 0.0.0
Requires-Python: >=3.10
License-File: LICENSE
Requires-Dist: numpy
